README.rst
setup.py
virtstrap_ruby_bundler/__init__.py
virtstrap_ruby_bundler/plugin.py
virtstrap_ruby_bundler.egg-info/PKG-INFO
virtstrap_ruby_bundler.egg-info/SOURCES.txt
virtstrap_ruby_bundler.egg-info/dependency_links.txt
virtstrap_ruby_bundler.egg-info/entry_points.txt
virtstrap_ruby_bundler.egg-info/not-zip-safe
virtstrap_ruby_bundler.egg-info/requires.txt
virtstrap_ruby_bundler.egg-info/top_level.txt