Metadata-Version: 1.0
Name: virtstrap-ruby-bundler
Version: 0.0.2
Summary: A virtstrap plugin that installs bundler Gemfiles
Home-page: UNKNOWN
Author: Reuven V. Gonzales
Author-email: reuven@tobetter.us
License: MIT
Keywords: virtstrap ruby bundler virtualenv pip
Platform: UNKNOWN
